package net.youmi.android;

import android.content.Context;
import java.io.InputStream;
import java.io.OutputStream;
import java.util.List;
import org.apache.http.HttpResponse;
import org.apache.http.impl.client.DefaultHttpClient;

abstract class bj
  implements ee
{
  protected String c;
  protected String d;
  protected long e;
  protected String f;
  protected final String g = "utf-8";
  protected Context h;
  protected DefaultHttpClient i;
  protected InputStream j;
  protected OutputStream k;
  protected List l;
  protected int m = 4;
  
  bj(Context paramContext, String paramString)
  {
    this.h = paramContext;
    this.c = paramString;
    this.d = paramString;
  }
  
  /* Error */
  private int a(int paramInt)
  {
    // Byte code:
    //   0: aload_0
    //   1: getfield 38	net/youmi/android/bj:h	Landroid/content/Context;
    //   4: invokestatic 51	net/youmi/android/dq:c	(Landroid/content/Context;)Z
    //   7: istore 10
    //   9: iload 10
    //   11: ifne +60 -> 71
    //   14: aload_0
    //   15: getfield 53	net/youmi/android/bj:k	Ljava/io/OutputStream;
    //   18: ifnull +10 -> 28
    //   21: aload_0
    //   22: getfield 53	net/youmi/android/bj:k	Ljava/io/OutputStream;
    //   25: invokevirtual 58	java/io/OutputStream:close	()V
    //   28: aload_0
    //   29: getfield 60	net/youmi/android/bj:j	Ljava/io/InputStream;
    //   32: ifnull +10 -> 42
    //   35: aload_0
    //   36: getfield 60	net/youmi/android/bj:j	Ljava/io/InputStream;
    //   39: invokevirtual 63	java/io/InputStream:close	()V
    //   42: aload_0
    //   43: getfield 65	net/youmi/android/bj:i	Lorg/apache/http/impl/client/DefaultHttpClient;
    //   46: astore 43
    //   48: iconst_0
    //   49: istore 21
    //   51: aload 43
    //   53: ifnull +15 -> 68
    //   56: aload_0
    //   57: getfield 65	net/youmi/android/bj:i	Lorg/apache/http/impl/client/DefaultHttpClient;
    //   60: invokevirtual 71	org/apache/http/impl/client/DefaultHttpClient:getConnectionManager	()Lorg/apache/http/conn/ClientConnectionManager;
    //   63: invokeinterface 76 1 0
    //   68: iload 21
    //   70: ireturn
    //   71: aload_0
    //   72: getfield 38	net/youmi/android/bj:h	Landroid/content/Context;
    //   75: invokestatic 81	net/youmi/android/s:b	(Landroid/content/Context;)Z
    //   78: istore 11
    //   80: iload 11
    //   82: ifne +52 -> 134
    //   85: aload_0
    //   86: getfield 53	net/youmi/android/bj:k	Ljava/io/OutputStream;
    //   89: ifnull +10 -> 99
    //   92: aload_0
    //   93: getfield 53	net/youmi/android/bj:k	Ljava/io/OutputStream;
    //   96: invokevirtual 58	java/io/OutputStream:close	()V
    //   99: aload_0
    //   100: getfield 60	net/youmi/android/bj:j	Ljava/io/InputStream;
    //   103: ifnull +10 -> 113
    //   106: aload_0
    //   107: getfield 60	net/youmi/android/bj:j	Ljava/io/InputStream;
    //   110: invokevirtual 63	java/io/InputStream:close	()V
    //   113: aload_0
    //   114: getfield 65	net/youmi/android/bj:i	Lorg/apache/http/impl/client/DefaultHttpClient;
    //   117: ifnull +15 -> 132
    //   120: aload_0
    //   121: getfield 65	net/youmi/android/bj:i	Lorg/apache/http/impl/client/DefaultHttpClient;
    //   124: invokevirtual 71	org/apache/http/impl/client/DefaultHttpClient:getConnectionManager	()Lorg/apache/http/conn/ClientConnectionManager;
    //   127: invokeinterface 76 1 0
    //   132: iconst_1
    //   133: ireturn
    //   134: aload_0
    //   135: aload_0
    //   136: getfield 38	net/youmi/android/bj:h	Landroid/content/Context;
    //   139: aload_0
    //   140: invokestatic 84	net/youmi/android/s:a	(Landroid/content/Context;Lnet/youmi/android/ee;)Lorg/apache/http/impl/client/DefaultHttpClient;
    //   143: putfield 65	net/youmi/android/bj:i	Lorg/apache/http/impl/client/DefaultHttpClient;
    //   146: iload_1
    //   147: iconst_1
    //   148: if_icmpne +152 -> 300
    //   151: new 86	org/apache/http/client/methods/HttpPost
    //   154: dup
    //   155: aload_0
    //   156: getfield 40	net/youmi/android/bj:c	Ljava/lang/String;
    //   159: invokespecial 89	org/apache/http/client/methods/HttpPost:<init>	(Ljava/lang/String;)V
    //   162: astore 12
    //   164: aload_0
    //   165: getfield 91	net/youmi/android/bj:l	Ljava/util/List;
    //   168: ifnull +33 -> 201
    //   171: aload_0
    //   172: getfield 91	net/youmi/android/bj:l	Ljava/util/List;
    //   175: invokeinterface 97 1 0
    //   180: ifle +21 -> 201
    //   183: aload 12
    //   185: new 99	org/apache/http/client/entity/UrlEncodedFormEntity
    //   188: dup
    //   189: aload_0
    //   190: getfield 91	net/youmi/android/bj:l	Ljava/util/List;
    //   193: ldc 32
    //   195: invokespecial 102	org/apache/http/client/entity/UrlEncodedFormEntity:<init>	(Ljava/util/List;Ljava/lang/String;)V
    //   198: invokevirtual 106	org/apache/http/client/methods/HttpPost:setEntity	(Lorg/apache/http/HttpEntity;)V
    //   201: aload_0
    //   202: getfield 65	net/youmi/android/bj:i	Lorg/apache/http/impl/client/DefaultHttpClient;
    //   205: aload 12
    //   207: invokevirtual 110	org/apache/http/impl/client/DefaultHttpClient:execute	(Lorg/apache/http/client/methods/HttpUriRequest;)Lorg/apache/http/HttpResponse;
    //   210: astore 13
    //   212: aload 13
    //   214: invokeinterface 116 1 0
    //   219: invokeinterface 121 1 0
    //   224: sipush 200
    //   227: if_icmpne +509 -> 736
    //   230: aload_0
    //   231: aload 13
    //   233: invokevirtual 124	net/youmi/android/bj:a	(Lorg/apache/http/HttpResponse;)Z
    //   236: ifne +131 -> 367
    //   239: aload_0
    //   240: getfield 36	net/youmi/android/bj:m	I
    //   243: istore 21
    //   245: aload_0
    //   246: getfield 53	net/youmi/android/bj:k	Ljava/io/OutputStream;
    //   249: ifnull +10 -> 259
    //   252: aload_0
    //   253: getfield 53	net/youmi/android/bj:k	Ljava/io/OutputStream;
    //   256: invokevirtual 58	java/io/OutputStream:close	()V
    //   259: aload_0
    //   260: getfield 60	net/youmi/android/bj:j	Ljava/io/InputStream;
    //   263: ifnull +10 -> 273
    //   266: aload_0
    //   267: getfield 60	net/youmi/android/bj:j	Ljava/io/InputStream;
    //   270: invokevirtual 63	java/io/InputStream:close	()V
    //   273: aload_0
    //   274: getfield 65	net/youmi/android/bj:i	Lorg/apache/http/impl/client/DefaultHttpClient;
    //   277: ifnull -209 -> 68
    //   280: aload_0
    //   281: getfield 65	net/youmi/android/bj:i	Lorg/apache/http/impl/client/DefaultHttpClient;
    //   284: invokevirtual 71	org/apache/http/impl/client/DefaultHttpClient:getConnectionManager	()Lorg/apache/http/conn/ClientConnectionManager;
    //   287: invokeinterface 76 1 0
    //   292: iload 21
    //   294: ireturn
    //   295: astore 36
    //   297: iload 21
    //   299: ireturn
    //   300: new 126	org/apache/http/client/methods/HttpGet
    //   303: dup
    //   304: aload_0
    //   305: getfield 40	net/youmi/android/bj:c	Ljava/lang/String;
    //   308: invokespecial 127	org/apache/http/client/methods/HttpGet:<init>	(Ljava/lang/String;)V
    //   311: astore 12
    //   313: goto -112 -> 201
    //   316: astore 6
    //   318: aload_0
    //   319: getfield 53	net/youmi/android/bj:k	Ljava/io/OutputStream;
    //   322: ifnull +10 -> 332
    //   325: aload_0
    //   326: getfield 53	net/youmi/android/bj:k	Ljava/io/OutputStream;
    //   329: invokevirtual 58	java/io/OutputStream:close	()V
    //   332: aload_0
    //   333: getfield 60	net/youmi/android/bj:j	Ljava/io/InputStream;
    //   336: ifnull +10 -> 346
    //   339: aload_0
    //   340: getfield 60	net/youmi/android/bj:j	Ljava/io/InputStream;
    //   343: invokevirtual 63	java/io/InputStream:close	()V
    //   346: aload_0
    //   347: getfield 65	net/youmi/android/bj:i	Lorg/apache/http/impl/client/DefaultHttpClient;
    //   350: ifnull +15 -> 365
    //   353: aload_0
    //   354: getfield 65	net/youmi/android/bj:i	Lorg/apache/http/impl/client/DefaultHttpClient;
    //   357: invokevirtual 71	org/apache/http/impl/client/DefaultHttpClient:getConnectionManager	()Lorg/apache/http/conn/ClientConnectionManager;
    //   360: invokeinterface 76 1 0
    //   365: iconst_2
    //   366: ireturn
    //   367: aload 13
    //   369: invokeinterface 131 1 0
    //   374: astore 17
    //   376: aload 17
    //   378: ifnull +309 -> 687
    //   381: aload_0
    //   382: aload 17
    //   384: invokeinterface 137 1 0
    //   389: putfield 139	net/youmi/android/bj:e	J
    //   392: aload_0
    //   393: aload 17
    //   395: invokeinterface 143 1 0
    //   400: putfield 60	net/youmi/android/bj:j	Ljava/io/InputStream;
    //   403: aload_0
    //   404: getfield 60	net/youmi/android/bj:j	Ljava/io/InputStream;
    //   407: ifnull +280 -> 687
    //   410: aload_0
    //   411: invokevirtual 146	net/youmi/android/bj:a	()Z
    //   414: ifeq +212 -> 626
    //   417: sipush 1024
    //   420: newarray byte
    //   422: astore 25
    //   424: aload_0
    //   425: getfield 60	net/youmi/android/bj:j	Ljava/io/InputStream;
    //   428: aload 25
    //   430: invokevirtual 150	java/io/InputStream:read	([B)I
    //   433: istore 26
    //   435: iload 26
    //   437: ifgt +63 -> 500
    //   440: aload_0
    //   441: invokevirtual 152	net/youmi/android/bj:b	()Z
    //   444: istore 27
    //   446: iload 27
    //   448: ifeq +117 -> 565
    //   451: aload_0
    //   452: getfield 53	net/youmi/android/bj:k	Ljava/io/OutputStream;
    //   455: ifnull +10 -> 465
    //   458: aload_0
    //   459: getfield 53	net/youmi/android/bj:k	Ljava/io/OutputStream;
    //   462: invokevirtual 58	java/io/OutputStream:close	()V
    //   465: aload_0
    //   466: getfield 60	net/youmi/android/bj:j	Ljava/io/InputStream;
    //   469: ifnull +10 -> 479
    //   472: aload_0
    //   473: getfield 60	net/youmi/android/bj:j	Ljava/io/InputStream;
    //   476: invokevirtual 63	java/io/InputStream:close	()V
    //   479: aload_0
    //   480: getfield 65	net/youmi/android/bj:i	Lorg/apache/http/impl/client/DefaultHttpClient;
    //   483: ifnull +15 -> 498
    //   486: aload_0
    //   487: getfield 65	net/youmi/android/bj:i	Lorg/apache/http/impl/client/DefaultHttpClient;
    //   490: invokevirtual 71	org/apache/http/impl/client/DefaultHttpClient:getConnectionManager	()Lorg/apache/http/conn/ClientConnectionManager;
    //   493: invokeinterface 76 1 0
    //   498: iconst_3
    //   499: ireturn
    //   500: aload_0
    //   501: getfield 53	net/youmi/android/bj:k	Ljava/io/OutputStream;
    //   504: aload 25
    //   506: iconst_0
    //   507: iload 26
    //   509: invokevirtual 156	java/io/OutputStream:write	([BII)V
    //   512: goto -88 -> 424
    //   515: astore_2
    //   516: aload_0
    //   517: getfield 53	net/youmi/android/bj:k	Ljava/io/OutputStream;
    //   520: ifnull +10 -> 530
    //   523: aload_0
    //   524: getfield 53	net/youmi/android/bj:k	Ljava/io/OutputStream;
    //   527: invokevirtual 58	java/io/OutputStream:close	()V
    //   530: aload_0
    //   531: getfield 60	net/youmi/android/bj:j	Ljava/io/InputStream;
    //   534: ifnull +10 -> 544
    //   537: aload_0
    //   538: getfield 60	net/youmi/android/bj:j	Ljava/io/InputStream;
    //   541: invokevirtual 63	java/io/InputStream:close	()V
    //   544: aload_0
    //   545: getfield 65	net/youmi/android/bj:i	Lorg/apache/http/impl/client/DefaultHttpClient;
    //   548: ifnull +15 -> 563
    //   551: aload_0
    //   552: getfield 65	net/youmi/android/bj:i	Lorg/apache/http/impl/client/DefaultHttpClient;
    //   555: invokevirtual 71	org/apache/http/impl/client/DefaultHttpClient:getConnectionManager	()Lorg/apache/http/conn/ClientConnectionManager;
    //   558: invokeinterface 76 1 0
    //   563: aload_2
    //   564: athrow
    //   565: aload_0
    //   566: getfield 36	net/youmi/android/bj:m	I
    //   569: istore 21
    //   571: aload_0
    //   572: getfield 53	net/youmi/android/bj:k	Ljava/io/OutputStream;
    //   575: ifnull +10 -> 585
    //   578: aload_0
    //   579: getfield 53	net/youmi/android/bj:k	Ljava/io/OutputStream;
    //   582: invokevirtual 58	java/io/OutputStream:close	()V
    //   585: aload_0
    //   586: getfield 60	net/youmi/android/bj:j	Ljava/io/InputStream;
    //   589: ifnull +10 -> 599
    //   592: aload_0
    //   593: getfield 60	net/youmi/android/bj:j	Ljava/io/InputStream;
    //   596: invokevirtual 63	java/io/InputStream:close	()V
    //   599: aload_0
    //   600: getfield 65	net/youmi/android/bj:i	Lorg/apache/http/impl/client/DefaultHttpClient;
    //   603: ifnull -535 -> 68
    //   606: aload_0
    //   607: getfield 65	net/youmi/android/bj:i	Lorg/apache/http/impl/client/DefaultHttpClient;
    //   610: invokevirtual 71	org/apache/http/impl/client/DefaultHttpClient:getConnectionManager	()Lorg/apache/http/conn/ClientConnectionManager;
    //   613: invokeinterface 76 1 0
    //   618: iload 21
    //   620: ireturn
    //   621: astore 30
    //   623: iload 21
    //   625: ireturn
    //   626: aload_0
    //   627: getfield 36	net/youmi/android/bj:m	I
    //   630: istore 21
    //   632: aload_0
    //   633: getfield 53	net/youmi/android/bj:k	Ljava/io/OutputStream;
    //   636: ifnull +10 -> 646
    //   639: aload_0
    //   640: getfield 53	net/youmi/android/bj:k	Ljava/io/OutputStream;
    //   643: invokevirtual 58	java/io/OutputStream:close	()V
    //   646: aload_0
    //   647: getfield 60	net/youmi/android/bj:j	Ljava/io/InputStream;
    //   650: ifnull +10 -> 660
    //   653: aload_0
    //   654: getfield 60	net/youmi/android/bj:j	Ljava/io/InputStream;
    //   657: invokevirtual 63	java/io/InputStream:close	()V
    //   660: aload_0
    //   661: getfield 65	net/youmi/android/bj:i	Lorg/apache/http/impl/client/DefaultHttpClient;
    //   664: ifnull -596 -> 68
    //   667: aload_0
    //   668: getfield 65	net/youmi/android/bj:i	Lorg/apache/http/impl/client/DefaultHttpClient;
    //   671: invokevirtual 71	org/apache/http/impl/client/DefaultHttpClient:getConnectionManager	()Lorg/apache/http/conn/ClientConnectionManager;
    //   674: invokeinterface 76 1 0
    //   679: iload 21
    //   681: ireturn
    //   682: astore 24
    //   684: iload 21
    //   686: ireturn
    //   687: aload_0
    //   688: getfield 53	net/youmi/android/bj:k	Ljava/io/OutputStream;
    //   691: ifnull +10 -> 701
    //   694: aload_0
    //   695: getfield 53	net/youmi/android/bj:k	Ljava/io/OutputStream;
    //   698: invokevirtual 58	java/io/OutputStream:close	()V
    //   701: aload_0
    //   702: getfield 60	net/youmi/android/bj:j	Ljava/io/InputStream;
    //   705: ifnull +10 -> 715
    //   708: aload_0
    //   709: getfield 60	net/youmi/android/bj:j	Ljava/io/InputStream;
    //   712: invokevirtual 63	java/io/InputStream:close	()V
    //   715: aload_0
    //   716: getfield 65	net/youmi/android/bj:i	Lorg/apache/http/impl/client/DefaultHttpClient;
    //   719: ifnull +15 -> 734
    //   722: aload_0
    //   723: getfield 65	net/youmi/android/bj:i	Lorg/apache/http/impl/client/DefaultHttpClient;
    //   726: invokevirtual 71	org/apache/http/impl/client/DefaultHttpClient:getConnectionManager	()Lorg/apache/http/conn/ClientConnectionManager;
    //   729: invokeinterface 76 1 0
    //   734: iconst_2
    //   735: ireturn
    //   736: aload_0
    //   737: getfield 53	net/youmi/android/bj:k	Ljava/io/OutputStream;
    //   740: ifnull +10 -> 750
    //   743: aload_0
    //   744: getfield 53	net/youmi/android/bj:k	Ljava/io/OutputStream;
    //   747: invokevirtual 58	java/io/OutputStream:close	()V
    //   750: aload_0
    //   751: getfield 60	net/youmi/android/bj:j	Ljava/io/InputStream;
    //   754: ifnull +10 -> 764
    //   757: aload_0
    //   758: getfield 60	net/youmi/android/bj:j	Ljava/io/InputStream;
    //   761: invokevirtual 63	java/io/InputStream:close	()V
    //   764: aload_0
    //   765: getfield 65	net/youmi/android/bj:i	Lorg/apache/http/impl/client/DefaultHttpClient;
    //   768: ifnull +15 -> 783
    //   771: aload_0
    //   772: getfield 65	net/youmi/android/bj:i	Lorg/apache/http/impl/client/DefaultHttpClient;
    //   775: invokevirtual 71	org/apache/http/impl/client/DefaultHttpClient:getConnectionManager	()Lorg/apache/http/conn/ClientConnectionManager;
    //   778: invokeinterface 76 1 0
    //   783: iconst_2
    //   784: ireturn
    //   785: astore 5
    //   787: goto -224 -> 563
    //   790: astore 4
    //   792: goto -248 -> 544
    //   795: astore_3
    //   796: goto -266 -> 530
    //   799: astore 9
    //   801: goto -436 -> 365
    //   804: astore 8
    //   806: goto -460 -> 346
    //   809: astore 7
    //   811: goto -479 -> 332
    //   814: astore 16
    //   816: goto -33 -> 783
    //   819: astore 15
    //   821: goto -57 -> 764
    //   824: astore 14
    //   826: goto -76 -> 750
    //   829: astore 20
    //   831: goto -97 -> 734
    //   834: astore 19
    //   836: goto -121 -> 715
    //   839: astore 18
    //   841: goto -140 -> 701
    //   844: astore 23
    //   846: goto -186 -> 660
    //   849: astore 22
    //   851: goto -205 -> 646
    //   854: astore 29
    //   856: goto -257 -> 599
    //   859: astore 28
    //   861: goto -276 -> 585
    //   864: astore 33
    //   866: goto -368 -> 498
    //   869: astore 32
    //   871: goto -392 -> 479
    //   874: astore 31
    //   876: goto -411 -> 465
    //   879: astore 35
    //   881: goto -608 -> 273
    //   884: astore 34
    //   886: goto -627 -> 259
    //   889: astore 39
    //   891: goto -759 -> 132
    //   894: astore 38
    //   896: goto -783 -> 113
    //   899: astore 37
    //   901: goto -802 -> 99
    //   904: astore 42
    //   906: iconst_0
    //   907: ireturn
    //   908: astore 41
    //   910: goto -868 -> 42
    //   913: astore 40
    //   915: goto -887 -> 28
    // Local variable table:
    //   start	length	slot	name	signature
    //   0	918	0	this	bj
    //   0	918	1	paramInt	int
    //   515	49	2	localObject1	Object
    //   795	1	3	localException1	java.lang.Exception
    //   790	1	4	localException2	java.lang.Exception
    //   785	1	5	localException3	java.lang.Exception
    //   316	1	6	localException4	java.lang.Exception
    //   809	1	7	localException5	java.lang.Exception
    //   804	1	8	localException6	java.lang.Exception
    //   799	1	9	localException7	java.lang.Exception
    //   7	3	10	bool1	boolean
    //   78	3	11	bool2	boolean
    //   162	150	12	localObject2	Object
    //   210	158	13	localHttpResponse	HttpResponse
    //   824	1	14	localException8	java.lang.Exception
    //   819	1	15	localException9	java.lang.Exception
    //   814	1	16	localException10	java.lang.Exception
    //   374	20	17	localHttpEntity	org.apache.http.HttpEntity
    //   839	1	18	localException11	java.lang.Exception
    //   834	1	19	localException12	java.lang.Exception
    //   829	1	20	localException13	java.lang.Exception
    //   49	636	21	n	int
    //   849	1	22	localException14	java.lang.Exception
    //   844	1	23	localException15	java.lang.Exception
    //   682	1	24	localException16	java.lang.Exception
    //   422	83	25	arrayOfByte	byte[]
    //   433	75	26	i1	int
    //   444	3	27	bool3	boolean
    //   859	1	28	localException17	java.lang.Exception
    //   854	1	29	localException18	java.lang.Exception
    //   621	1	30	localException19	java.lang.Exception
    //   874	1	31	localException20	java.lang.Exception
    //   869	1	32	localException21	java.lang.Exception
    //   864	1	33	localException22	java.lang.Exception
    //   884	1	34	localException23	java.lang.Exception
    //   879	1	35	localException24	java.lang.Exception
    //   295	1	36	localException25	java.lang.Exception
    //   899	1	37	localException26	java.lang.Exception
    //   894	1	38	localException27	java.lang.Exception
    //   889	1	39	localException28	java.lang.Exception
    //   913	1	40	localException29	java.lang.Exception
    //   908	1	41	localException30	java.lang.Exception
    //   904	1	42	localException31	java.lang.Exception
    //   46	6	43	localDefaultHttpClient	DefaultHttpClient
    // Exception table:
    //   from	to	target	type
    //   273	292	295	java/lang/Exception
    //   0	9	316	java/lang/Exception
    //   71	80	316	java/lang/Exception
    //   134	146	316	java/lang/Exception
    //   151	201	316	java/lang/Exception
    //   201	245	316	java/lang/Exception
    //   300	313	316	java/lang/Exception
    //   367	376	316	java/lang/Exception
    //   381	424	316	java/lang/Exception
    //   424	435	316	java/lang/Exception
    //   440	446	316	java/lang/Exception
    //   500	512	316	java/lang/Exception
    //   565	571	316	java/lang/Exception
    //   626	632	316	java/lang/Exception
    //   0	9	515	finally
    //   71	80	515	finally
    //   134	146	515	finally
    //   151	201	515	finally
    //   201	245	515	finally
    //   300	313	515	finally
    //   367	376	515	finally
    //   381	424	515	finally
    //   424	435	515	finally
    //   440	446	515	finally
    //   500	512	515	finally
    //   565	571	515	finally
    //   626	632	515	finally
    //   599	618	621	java/lang/Exception
    //   660	679	682	java/lang/Exception
    //   544	563	785	java/lang/Exception
    //   530	544	790	java/lang/Exception
    //   516	530	795	java/lang/Exception
    //   346	365	799	java/lang/Exception
    //   332	346	804	java/lang/Exception
    //   318	332	809	java/lang/Exception
    //   764	783	814	java/lang/Exception
    //   750	764	819	java/lang/Exception
    //   736	750	824	java/lang/Exception
    //   715	734	829	java/lang/Exception
    //   701	715	834	java/lang/Exception
    //   687	701	839	java/lang/Exception
    //   646	660	844	java/lang/Exception
    //   632	646	849	java/lang/Exception
    //   585	599	854	java/lang/Exception
    //   571	585	859	java/lang/Exception
    //   479	498	864	java/lang/Exception
    //   465	479	869	java/lang/Exception
    //   451	465	874	java/lang/Exception
    //   259	273	879	java/lang/Exception
    //   245	259	884	java/lang/Exception
    //   113	132	889	java/lang/Exception
    //   99	113	894	java/lang/Exception
    //   85	99	899	java/lang/Exception
    //   42	48	904	java/lang/Exception
    //   56	68	904	java/lang/Exception
    //   28	42	908	java/lang/Exception
    //   14	28	913	java/lang/Exception
  }
  
  int a(List paramList)
  {
    this.l = paramList;
    return a(1);
  }
  
  public void a(String paramString)
  {
    this.d = paramString;
  }
  
  protected abstract boolean a();
  
  protected abstract boolean a(HttpResponse paramHttpResponse);
  
  protected abstract boolean b();
}


/* Location:           J:\android\tools\dex2jar-0.0.9.15\classes_dex2jar.jar
 * Qualified Name:     net.youmi.android.bj
 * JD-Core Version:    0.7.0.1
 */