package net.youmi.android;

import android.graphics.Bitmap;

class cu
{
  static String a = "00000000";
  private em A;
  private cr B;
  private long b = 0L;
  private long c = 0L;
  private boolean d = false;
  private boolean e = false;
  private boolean f = false;
  private boolean g = true;
  private boolean h = false;
  private boolean i = false;
  private int j = 11;
  private int k = 1;
  private String l;
  private String m;
  private String n;
  private String o;
  private String p;
  private String q;
  private String r;
  private String s;
  private String t;
  private String u;
  private String[] v;
  private Bitmap w;
  private Bitmap x;
  private Bitmap y;
  private em z;
  
  /* Error */
  static cu a(android.content.Context paramContext, boolean paramBoolean1, String paramString1, String paramString2, String paramString3, int paramInt1, int paramInt2, String paramString4, String paramString5, String paramString6, String paramString7, String paramString8, String paramString9, String paramString10, String paramString11, String paramString12, java.util.ArrayList paramArrayList, boolean paramBoolean2, boolean paramBoolean3, String paramString13, long paramLong)
  {
    // Byte code:
    //   0: aload_2
    //   1: ifnonnull +5 -> 6
    //   4: aconst_null
    //   5: areturn
    //   6: aload_2
    //   7: invokevirtual 78	java/lang/String:trim	()Ljava/lang/String;
    //   10: astore 23
    //   12: aload 23
    //   14: invokevirtual 82	java/lang/String:length	()I
    //   17: ifne +1058 -> 1075
    //   20: aconst_null
    //   21: areturn
    //   22: aload_3
    //   23: invokevirtual 78	java/lang/String:trim	()Ljava/lang/String;
    //   26: astore 24
    //   28: aload 24
    //   30: invokevirtual 82	java/lang/String:length	()I
    //   33: ifne +1048 -> 1081
    //   36: aconst_null
    //   37: areturn
    //   38: aload 4
    //   40: invokevirtual 78	java/lang/String:trim	()Ljava/lang/String;
    //   43: astore 25
    //   45: aload 25
    //   47: invokevirtual 82	java/lang/String:length	()I
    //   50: ifne +5 -> 55
    //   53: aconst_null
    //   54: areturn
    //   55: iload 5
    //   57: invokestatic 87	net/youmi/android/bt:a	(I)Z
    //   60: ifne +5 -> 65
    //   63: aconst_null
    //   64: areturn
    //   65: iload 6
    //   67: invokestatic 90	net/youmi/android/ev:a	(I)Z
    //   70: ifne +5 -> 75
    //   73: aconst_null
    //   74: areturn
    //   75: new 2	net/youmi/android/cu
    //   78: dup
    //   79: invokespecial 91	net/youmi/android/cu:<init>	()V
    //   82: astore 26
    //   84: aload 26
    //   86: lload 20
    //   88: putfield 53	net/youmi/android/cu:c	J
    //   91: aload 26
    //   93: invokestatic 97	java/lang/System:currentTimeMillis	()J
    //   96: putfield 51	net/youmi/android/cu:b	J
    //   99: aload 26
    //   101: aload 23
    //   103: putfield 99	net/youmi/android/cu:o	Ljava/lang/String;
    //   106: aload 26
    //   108: aload 24
    //   110: putfield 101	net/youmi/android/cu:l	Ljava/lang/String;
    //   113: aload 26
    //   115: aload 25
    //   117: putfield 103	net/youmi/android/cu:n	Ljava/lang/String;
    //   120: aload 26
    //   122: iload 5
    //   124: putfield 69	net/youmi/android/cu:k	I
    //   127: aload 26
    //   129: iload 6
    //   131: putfield 67	net/youmi/android/cu:j	I
    //   134: aload 19
    //   136: ifnull +952 -> 1088
    //   139: aload 19
    //   141: invokevirtual 78	java/lang/String:trim	()Ljava/lang/String;
    //   144: astore 27
    //   146: aload 27
    //   148: invokevirtual 82	java/lang/String:length	()I
    //   151: ifle +937 -> 1088
    //   154: aload 26
    //   156: aload 27
    //   158: putfield 105	net/youmi/android/cu:u	Ljava/lang/String;
    //   161: goto +927 -> 1088
    //   164: aload 7
    //   166: invokevirtual 78	java/lang/String:trim	()Ljava/lang/String;
    //   169: astore 28
    //   171: aload 28
    //   173: invokevirtual 82	java/lang/String:length	()I
    //   176: ifle +269 -> 445
    //   179: aload 28
    //   181: invokevirtual 82	java/lang/String:length	()I
    //   184: bipush 8
    //   186: if_icmple +188 -> 374
    //   189: aload 28
    //   191: bipush 248
    //   193: aload 28
    //   195: invokevirtual 82	java/lang/String:length	()I
    //   198: iadd
    //   199: invokevirtual 109	java/lang/String:substring	(I)Ljava/lang/String;
    //   202: astore 28
    //   204: aload 26
    //   206: aload 28
    //   208: putfield 111	net/youmi/android/cu:m	Ljava/lang/String;
    //   211: aload 26
    //   213: iload 17
    //   215: putfield 59	net/youmi/android/cu:f	Z
    //   218: aload 26
    //   220: iload 18
    //   222: putfield 61	net/youmi/android/cu:g	Z
    //   225: aload 8
    //   227: ifnull +25 -> 252
    //   230: aload 8
    //   232: invokevirtual 78	java/lang/String:trim	()Ljava/lang/String;
    //   235: astore 29
    //   237: aload 29
    //   239: invokevirtual 82	java/lang/String:length	()I
    //   242: ifle +10 -> 252
    //   245: aload 26
    //   247: aload 29
    //   249: putfield 113	net/youmi/android/cu:p	Ljava/lang/String;
    //   252: aload 9
    //   254: ifnull +25 -> 279
    //   257: aload 9
    //   259: invokevirtual 78	java/lang/String:trim	()Ljava/lang/String;
    //   262: astore 30
    //   264: aload 30
    //   266: invokevirtual 82	java/lang/String:length	()I
    //   269: ifle +10 -> 279
    //   272: aload 26
    //   274: aload 30
    //   276: putfield 115	net/youmi/android/cu:q	Ljava/lang/String;
    //   279: aload 26
    //   281: getfield 113	net/youmi/android/cu:p	Ljava/lang/String;
    //   284: ifnonnull +27 -> 311
    //   287: aload 26
    //   289: getfield 115	net/youmi/android/cu:q	Ljava/lang/String;
    //   292: ifnull +19 -> 311
    //   295: aload 26
    //   297: aload 26
    //   299: getfield 115	net/youmi/android/cu:q	Ljava/lang/String;
    //   302: putfield 113	net/youmi/android/cu:p	Ljava/lang/String;
    //   305: aload 26
    //   307: aconst_null
    //   308: putfield 115	net/youmi/android/cu:q	Ljava/lang/String;
    //   311: aload 13
    //   313: ifnull +801 -> 1114
    //   316: aload 13
    //   318: invokevirtual 78	java/lang/String:trim	()Ljava/lang/String;
    //   321: astore 31
    //   323: aload 14
    //   325: ifnull +796 -> 1121
    //   328: aload 14
    //   330: invokevirtual 78	java/lang/String:trim	()Ljava/lang/String;
    //   333: astore 32
    //   335: aload 26
    //   337: aload 31
    //   339: putfield 117	net/youmi/android/cu:s	Ljava/lang/String;
    //   342: aload 26
    //   344: aload 32
    //   346: putfield 119	net/youmi/android/cu:t	Ljava/lang/String;
    //   349: aload 31
    //   351: invokevirtual 82	java/lang/String:length	()I
    //   354: ifgt +11 -> 365
    //   357: aload 32
    //   359: invokevirtual 82	java/lang/String:length	()I
    //   362: ifle +90 -> 452
    //   365: aload 26
    //   367: iconst_1
    //   368: putfield 65	net/youmi/android/cu:i	Z
    //   371: goto +729 -> 1100
    //   374: aload 28
    //   376: invokevirtual 82	java/lang/String:length	()I
    //   379: istore 52
    //   381: iload 52
    //   383: bipush 8
    //   385: if_icmpge -181 -> 204
    //   388: new 121	java/lang/StringBuilder
    //   391: dup
    //   392: invokespecial 122	java/lang/StringBuilder:<init>	()V
    //   395: astore 53
    //   397: iconst_0
    //   398: istore 54
    //   400: iload 54
    //   402: bipush 8
    //   404: aload 28
    //   406: invokevirtual 82	java/lang/String:length	()I
    //   409: isub
    //   410: if_icmplt +21 -> 431
    //   413: aload 53
    //   415: aload 28
    //   417: invokevirtual 126	java/lang/StringBuilder:append	(Ljava/lang/String;)Ljava/lang/StringBuilder;
    //   420: pop
    //   421: aload 53
    //   423: invokevirtual 129	java/lang/StringBuilder:toString	()Ljava/lang/String;
    //   426: astore 28
    //   428: goto -224 -> 204
    //   431: aload 53
    //   433: bipush 48
    //   435: invokevirtual 132	java/lang/StringBuilder:append	(C)Ljava/lang/StringBuilder;
    //   438: pop
    //   439: iinc 54 1
    //   442: goto -42 -> 400
    //   445: ldc 44
    //   447: astore 28
    //   449: goto -245 -> 204
    //   452: aload 26
    //   454: iconst_0
    //   455: putfield 65	net/youmi/android/cu:i	Z
    //   458: goto +642 -> 1100
    //   461: astore 22
    //   463: aload 22
    //   465: invokestatic 137	net/youmi/android/f:a	(Ljava/lang/Throwable;)V
    //   468: aconst_null
    //   469: areturn
    //   470: aload 15
    //   472: invokevirtual 78	java/lang/String:trim	()Ljava/lang/String;
    //   475: astore 33
    //   477: aload 33
    //   479: invokevirtual 82	java/lang/String:length	()I
    //   482: ifne +12 -> 494
    //   485: iload 6
    //   487: bipush 31
    //   489: if_icmpeq +5 -> 494
    //   492: aconst_null
    //   493: areturn
    //   494: aload 26
    //   496: aload 33
    //   498: putfield 139	net/youmi/android/cu:r	Ljava/lang/String;
    //   501: aload 16
    //   503: ifnull +37 -> 540
    //   506: aload 16
    //   508: invokevirtual 144	java/util/ArrayList:size	()I
    //   511: ifle +29 -> 540
    //   514: aload 26
    //   516: aload 16
    //   518: invokevirtual 144	java/util/ArrayList:size	()I
    //   521: anewarray 74	java/lang/String
    //   524: putfield 146	net/youmi/android/cu:v	[Ljava/lang/String;
    //   527: iconst_0
    //   528: istore 51
    //   530: iload 51
    //   532: aload 16
    //   534: invokevirtual 144	java/util/ArrayList:size	()I
    //   537: if_icmplt +111 -> 648
    //   540: aload 26
    //   542: invokevirtual 148	net/youmi/android/cu:b	()I
    //   545: iconst_1
    //   546: if_icmpne +14 -> 560
    //   549: aload 10
    //   551: ifnonnull +121 -> 672
    //   554: aload 26
    //   556: iconst_0
    //   557: putfield 69	net/youmi/android/cu:k	I
    //   560: aload 11
    //   562: ifnull +46 -> 608
    //   565: aload 11
    //   567: invokevirtual 78	java/lang/String:trim	()Ljava/lang/String;
    //   570: astore 34
    //   572: aload 34
    //   574: invokevirtual 82	java/lang/String:length	()I
    //   577: istore 35
    //   579: iload 35
    //   581: ifle +27 -> 608
    //   584: invokestatic 153	net/youmi/android/bc:a	()Lnet/youmi/android/ed;
    //   587: aload 34
    //   589: invokevirtual 158	net/youmi/android/ed:e	(Ljava/lang/String;)Z
    //   592: ifeq +212 -> 804
    //   595: aload 26
    //   597: invokestatic 153	net/youmi/android/bc:a	()Lnet/youmi/android/ed;
    //   600: aload 34
    //   602: invokevirtual 161	net/youmi/android/ed:g	(Ljava/lang/String;)Landroid/graphics/Bitmap;
    //   605: putfield 163	net/youmi/android/cu:x	Landroid/graphics/Bitmap;
    //   608: aload 12
    //   610: ifnonnull +242 -> 852
    //   613: ldc 165
    //   615: astore 36
    //   617: aload 26
    //   619: getfield 69	net/youmi/android/cu:k	I
    //   622: tableswitch	default:+506 -> 1128, 2:+240->862, 3:+295->917, 4:+350->972
    //   649: iload_0
    //   650: getfield 146	net/youmi/android/cu:v	[Ljava/lang/String;
    //   653: iload 51
    //   655: aload 16
    //   657: iload 51
    //   659: invokevirtual 169	java/util/ArrayList:get	(I)Ljava/lang/Object;
    //   662: checkcast 74	java/lang/String
    //   665: aastore
    //   666: iinc 51 1
    //   669: goto -139 -> 530
    //   672: aload 10
    //   674: invokevirtual 78	java/lang/String:trim	()Ljava/lang/String;
    //   677: astore 46
    //   679: aload 46
    //   681: invokevirtual 82	java/lang/String:length	()I
    //   684: istore 47
    //   686: iload 47
    //   688: ifle +107 -> 795
    //   691: invokestatic 153	net/youmi/android/bc:a	()Lnet/youmi/android/ed;
    //   694: aload 46
    //   696: invokevirtual 158	net/youmi/android/ed:e	(Ljava/lang/String;)Z
    //   699: ifeq +16 -> 715
    //   702: aload 26
    //   704: invokestatic 153	net/youmi/android/bc:a	()Lnet/youmi/android/ed;
    //   707: aload 46
    //   709: invokevirtual 161	net/youmi/android/ed:g	(Ljava/lang/String;)Landroid/graphics/Bitmap;
    //   712: putfield 171	net/youmi/android/cu:w	Landroid/graphics/Bitmap;
    //   715: aload 26
    //   717: getfield 171	net/youmi/android/cu:w	Landroid/graphics/Bitmap;
    //   720: ifnonnull -160 -> 560
    //   723: new 173	net/youmi/android/bz
    //   726: dup
    //   727: invokestatic 153	net/youmi/android/bc:a	()Lnet/youmi/android/ed;
    //   730: invokespecial 176	net/youmi/android/bz:<init>	(Lnet/youmi/android/ed;)V
    //   733: astore 50
    //   735: aload 50
    //   737: aload_0
    //   738: aload 46
    //   740: invokevirtual 179	net/youmi/android/bz:a	(Landroid/content/Context;Ljava/lang/String;)I
    //   743: bipush 6
    //   745: if_icmpne +41 -> 786
    //   748: aload 26
    //   750: aload 50
    //   752: invokevirtual 182	net/youmi/android/bz:c	()Landroid/graphics/Bitmap;
    //   755: putfield 171	net/youmi/android/cu:w	Landroid/graphics/Bitmap;
    //   758: aload 26
    //   760: getfield 171	net/youmi/android/cu:w	Landroid/graphics/Bitmap;
    //   763: ifnonnull -203 -> 560
    //   766: aload 26
    //   768: iconst_0
    //   769: putfield 69	net/youmi/android/cu:k	I
    //   772: goto -212 -> 560
    //   775: astore 49
    //   777: aload 26
    //   779: iconst_0
    //   780: putfield 69	net/youmi/android/cu:k	I
    //   783: goto -223 -> 560
    //   786: aload 26
    //   788: iconst_0
    //   789: putfield 69	net/youmi/android/cu:k	I
    //   792: goto -232 -> 560
    //   795: aload 26
    //   797: iconst_0
    //   798: putfield 69	net/youmi/android/cu:k	I
    //   801: goto -241 -> 560
    //   804: new 173	net/youmi/android/bz
    //   807: dup
    //   808: invokestatic 153	net/youmi/android/bc:a	()Lnet/youmi/android/ed;
    //   811: invokespecial 176	net/youmi/android/bz:<init>	(Lnet/youmi/android/ed;)V
    //   814: astore 45
    //   816: aload 45
    //   818: aload_0
    //   819: aload 34
    //   821: invokevirtual 179	net/youmi/android/bz:a	(Landroid/content/Context;Ljava/lang/String;)I
    //   824: bipush 6
    //   826: if_icmpne -218 -> 608
    //   829: aload 26
    //   831: aload 45
    //   833: invokevirtual 182	net/youmi/android/bz:c	()Landroid/graphics/Bitmap;
    //   836: putfield 163	net/youmi/android/cu:x	Landroid/graphics/Bitmap;
    //   839: goto -231 -> 608
    //   842: astore 44
    //   844: aload 44
    //   846: invokestatic 137	net/youmi/android/f:a	(Ljava/lang/Throwable;)V
    //   849: goto -241 -> 608
    //   852: aload 12
    //   854: invokevirtual 78	java/lang/String:trim	()Ljava/lang/String;
    //   857: astore 36
    //   859: goto -242 -> 617
    //   862: aload 36
    //   864: invokevirtual 82	java/lang/String:length	()I
    //   867: ifne +5 -> 872
    //   870: aconst_null
    //   871: areturn
    //   872: new 173	net/youmi/android/bz
    //   875: dup
    //   876: invokestatic 184	net/youmi/android/bc:b	()Lnet/youmi/android/ed;
    //   879: invokespecial 176	net/youmi/android/bz:<init>	(Lnet/youmi/android/ed;)V
    //   882: astore 43
    //   884: aload 43
    //   886: aload_0
    //   887: aload 36
    //   889: invokevirtual 179	net/youmi/android/bz:a	(Landroid/content/Context;Ljava/lang/String;)I
    //   892: bipush 6
    //   894: if_icmpne +13 -> 907
    //   897: aload 26
    //   899: aload 43
    //   901: invokevirtual 182	net/youmi/android/bz:c	()Landroid/graphics/Bitmap;
    //   904: putfield 186	net/youmi/android/cu:y	Landroid/graphics/Bitmap;
    //   907: aload 26
    //   909: getfield 186	net/youmi/android/cu:y	Landroid/graphics/Bitmap;
    //   912: ifnonnull +216 -> 1128
    //   915: aconst_null
    //   916: areturn
    //   917: aload 36
    //   919: invokevirtual 82	java/lang/String:length	()I
    //   922: ifne +5 -> 927
    //   925: aconst_null
    //   926: areturn
    //   927: new 188	net/youmi/android/dd
    //   930: dup
    //   931: invokestatic 190	net/youmi/android/bc:c	()Lnet/youmi/android/ed;
    //   934: invokespecial 191	net/youmi/android/dd:<init>	(Lnet/youmi/android/ed;)V
    //   937: astore 42
    //   939: aload 42
    //   941: aload_0
    //   942: aload 36
    //   944: invokevirtual 192	net/youmi/android/dd:a	(Landroid/content/Context;Ljava/lang/String;)I
    //   947: bipush 6
    //   949: if_icmpne +13 -> 962
    //   952: aload 26
    //   954: aload 42
    //   956: invokevirtual 195	net/youmi/android/dd:c	()Lnet/youmi/android/cr;
    //   959: putfield 197	net/youmi/android/cu:B	Lnet/youmi/android/cr;
    //   962: aload 26
    //   964: getfield 197	net/youmi/android/cu:B	Lnet/youmi/android/cr;
    //   967: ifnonnull +161 -> 1128
    //   970: aconst_null
    //   971: areturn
    //   972: new 199	net/youmi/android/bl
    //   975: dup
    //   976: invokespecial 200	net/youmi/android/bl:<init>	()V
    //   979: astore 37
    //   981: aload 37
    //   983: aload_0
    //   984: aload 36
    //   986: invokevirtual 201	net/youmi/android/bl:a	(Landroid/content/Context;Ljava/lang/String;)I
    //   989: istore 38
    //   991: aconst_null
    //   992: astore 39
    //   994: iload 38
    //   996: bipush 6
    //   998: if_icmpne +133 -> 1131
    //   1001: aload 37
    //   1003: invokevirtual 203	net/youmi/android/bl:c	()Ljava/lang/String;
    //   1006: astore 40
    //   1008: aconst_null
    //   1009: astore 39
    //   1011: aload 40
    //   1013: ifnull +118 -> 1131
    //   1016: aload 37
    //   1018: invokevirtual 205	net/youmi/android/bl:h	()Ljava/lang/String;
    //   1021: aload 40
    //   1023: invokestatic 210	net/youmi/android/ba:a	(Ljava/lang/String;Ljava/lang/String;)Ljava/lang/String;
    //   1026: astore 41
    //   1028: aconst_null
    //   1029: astore 39
    //   1031: aload 41
    //   1033: ifnull +98 -> 1131
    //   1036: new 212	net/youmi/android/em
    //   1039: dup
    //   1040: aload 37
    //   1042: invokevirtual 205	net/youmi/android/bl:h	()Ljava/lang/String;
    //   1045: aload 41
    //   1047: invokespecial 215	net/youmi/android/em:<init>	(Ljava/lang/String;Ljava/lang/String;)V
    //   1050: astore 39
    //   1052: goto +79 -> 1131
    //   1055: aload 26
    //   1057: aload 39
    //   1059: putfield 217	net/youmi/android/cu:A	Lnet/youmi/android/em;
    //   1062: goto +66 -> 1128
    //   1065: astore 48
    //   1067: goto -352 -> 715
    //   1070: astore 55
    //   1072: goto -868 -> 204
    //   1075: aload_3
    //   1076: ifnonnull -1054 -> 22
    //   1079: aconst_null
    //   1080: areturn
    //   1081: aload 4
    //   1083: ifnonnull -1045 -> 38
    //   1086: aconst_null
    //   1087: areturn
    //   1088: aload 7
    //   1090: ifnonnull -926 -> 164
    //   1093: ldc 44
    //   1095: astore 7
    //   1097: goto -933 -> 164
    //   1100: aload 15
    //   1102: ifnonnull -632 -> 470
    //   1105: iload 6
    //   1107: bipush 31
    //   1109: if_icmpeq -639 -> 470
    //   1112: aconst_null
    //   1113: areturn
    //   1114: ldc 165
    //   1116: astore 31
    //   1118: goto -795 -> 323
    //   1121: ldc 165
    //   1123: astore 32
    //   1125: goto -790 -> 335
    //   1128: aload 26
    //   1130: areturn
    //   1131: aload 39
    //   1133: ifnonnull -78 -> 1055
    //   1136: aconst_null
    //   1137: areturn
    // Local variable table:
    //   start	length	slot	name	signature
    //   0	1138	0	paramContext	android.content.Context
    //   0	1138	1	paramBoolean1	boolean
    //   0	1138	2	paramString1	String
    //   0	1138	3	paramString2	String
    //   0	1138	4	paramString3	String
    //   0	1138	5	paramInt1	int
    //   0	1138	6	paramInt2	int
    //   0	1138	7	paramString4	String
    //   0	1138	8	paramString5	String
    //   0	1138	9	paramString6	String
    //   0	1138	10	paramString7	String
    //   0	1138	11	paramString8	String
    //   0	1138	12	paramString9	String
    //   0	1138	13	paramString10	String
    //   0	1138	14	paramString11	String
    //   0	1138	15	paramString12	String
    //   0	1138	16	paramArrayList	java.util.ArrayList
    //   0	1138	17	paramBoolean2	boolean
    //   0	1138	18	paramBoolean3	boolean
    //   0	1138	19	paramString13	String
    //   0	1138	20	paramLong	long
    //   461	3	22	localException1	java.lang.Exception
    //   10	92	23	str1	String
    //   26	83	24	str2	String
    //   43	73	25	str3	String
    //   82	1047	26	localcu	cu
    //   144	13	27	str4	String
    //   169	279	28	str5	String
    //   235	13	29	str6	String
    //   262	13	30	str7	String
    //   321	796	31	str8	String
    //   333	791	32	str9	String
    //   475	22	33	str10	String
    //   570	250	34	str11	String
    //   577	3	35	i1	int
    //   615	370	36	str12	String
    //   979	62	37	localbl	bl
    //   989	10	38	i2	int
    //   992	140	39	localem	em
    //   1006	16	40	str13	String
    //   1026	20	41	str14	String
    //   937	18	42	localdd	dd
    //   882	18	43	localbz1	bz
    //   842	3	44	localException2	java.lang.Exception
    //   814	18	45	localbz2	bz
    //   677	62	46	str15	String
    //   684	3	47	i3	int
    //   1065	1	48	localException3	java.lang.Exception
    //   775	1	49	localException4	java.lang.Exception
    //   733	18	50	localbz3	bz
    //   528	139	51	i4	int
    //   379	7	52	i5	int
    //   395	37	53	localStringBuilder	java.lang.StringBuilder
    //   398	42	54	i6	int
    //   1070	1	55	localException5	java.lang.Exception
    // Exception table:
    //   from	to	target	type
    //   6	20	461	java/lang/Exception
    //   22	36	461	java/lang/Exception
    //   38	53	461	java/lang/Exception
    //   55	63	461	java/lang/Exception
    //   65	73	461	java/lang/Exception
    //   75	134	461	java/lang/Exception
    //   139	161	461	java/lang/Exception
    //   164	204	461	java/lang/Exception
    //   204	225	461	java/lang/Exception
    //   230	252	461	java/lang/Exception
    //   257	279	461	java/lang/Exception
    //   279	311	461	java/lang/Exception
    //   316	323	461	java/lang/Exception
    //   328	335	461	java/lang/Exception
    //   335	365	461	java/lang/Exception
    //   365	371	461	java/lang/Exception
    //   374	381	461	java/lang/Exception
    //   452	458	461	java/lang/Exception
    //   470	485	461	java/lang/Exception
    //   494	501	461	java/lang/Exception
    //   506	527	461	java/lang/Exception
    //   530	540	461	java/lang/Exception
    //   540	549	461	java/lang/Exception
    //   554	560	461	java/lang/Exception
    //   565	579	461	java/lang/Exception
    //   617	648	461	java/lang/Exception
    //   648	666	461	java/lang/Exception
    //   672	686	461	java/lang/Exception
    //   777	783	461	java/lang/Exception
    //   795	801	461	java/lang/Exception
    //   844	849	461	java/lang/Exception
    //   852	859	461	java/lang/Exception
    //   862	870	461	java/lang/Exception
    //   872	907	461	java/lang/Exception
    //   907	915	461	java/lang/Exception
    //   917	925	461	java/lang/Exception
    //   927	962	461	java/lang/Exception
    //   962	970	461	java/lang/Exception
    //   972	991	461	java/lang/Exception
    //   1001	1008	461	java/lang/Exception
    //   1016	1028	461	java/lang/Exception
    //   1036	1052	461	java/lang/Exception
    //   1055	1062	461	java/lang/Exception
    //   715	772	775	java/lang/Exception
    //   786	792	775	java/lang/Exception
    //   584	608	842	java/lang/Exception
    //   804	839	842	java/lang/Exception
    //   691	715	1065	java/lang/Exception
    //   388	397	1070	java/lang/Exception
    //   400	428	1070	java/lang/Exception
    //   431	439	1070	java/lang/Exception
  }
  
  long A()
  {
    return this.b;
  }
  
  long B()
  {
    return this.c;
  }
  
  int a()
  {
    return this.j;
  }
  
  void a(em paramem)
  {
    this.z = paramem;
  }
  
  int b()
  {
    return this.k;
  }
  
  String c()
  {
    return this.p;
  }
  
  String d()
  {
    return this.q;
  }
  
  Bitmap e()
  {
    if (this.k == 1) {
      return this.w;
    }
    if (this.k == 2) {
      return this.y;
    }
    return null;
  }
  
  String f()
  {
    return this.o;
  }
  
  String g()
  {
    return this.s;
  }
  
  String h()
  {
    return this.t;
  }
  
  em i()
  {
    return this.z;
  }
  
  em j()
  {
    return this.A;
  }
  
  String k()
  {
    return this.n;
  }
  
  String l()
  {
    return this.m;
  }
  
  cr m()
  {
    return this.B;
  }
  
  Bitmap n()
  {
    return this.x;
  }
  
  String o()
  {
    return this.l;
  }
  
  String p()
  {
    return this.r;
  }
  
  boolean q()
  {
    return this.h;
  }
  
  void r()
  {
    this.h = true;
  }
  
  boolean s()
  {
    return this.d;
  }
  
  boolean t()
  {
    return this.e;
  }
  
  boolean u()
  {
    return this.g;
  }
  
  void v()
  {
    this.d = true;
  }
  
  void w()
  {
    this.e = true;
  }
  
  String[] x()
  {
    return this.v;
  }
  
  boolean y()
  {
    return this.f;
  }
  
  String z()
  {
    return this.u;
  }
}


/* Location:           J:\android\tools\dex2jar-0.0.9.15\classes_dex2jar.jar
 * Qualified Name:     net.youmi.android.cu
 * JD-Core Version:    0.7.0.1
 */