package net.youmi.android;

import android.view.View.OnClickListener;

class eg
  implements View.OnClickListener
{
  eg(cb paramcb) {}
  
  /* Error */
  public void onClick(android.view.View paramView)
  {
    // Byte code:
    //   0: invokestatic 25	net/youmi/android/bc:g	()Lnet/youmi/android/ed;
    //   3: aload_0
    //   4: getfield 12	net/youmi/android/eg:a	Lnet/youmi/android/cb;
    //   7: getfield 31	net/youmi/android/cb:c	Ljava/lang/String;
    //   10: invokevirtual 36	net/youmi/android/ed:a	(Ljava/lang/String;)Ljava/lang/String;
    //   13: astore_3
    //   14: aload_0
    //   15: getfield 12	net/youmi/android/eg:a	Lnet/youmi/android/cb;
    //   18: getfield 40	net/youmi/android/cb:b	Landroid/app/Activity;
    //   21: aload_3
    //   22: aconst_null
    //   23: aconst_null
    //   24: aconst_null
    //   25: aconst_null
    //   26: invokestatic 45	net/youmi/android/k:a	(Landroid/content/Context;Ljava/lang/String;Ljava/lang/String;Ljava/lang/String;Ljava/lang/String;Ljava/lang/String;)Lnet/youmi/android/bw;
    //   29: astore 6
    //   31: aload_0
    //   32: getfield 12	net/youmi/android/eg:a	Lnet/youmi/android/cb;
    //   35: getfield 40	net/youmi/android/cb:b	Landroid/app/Activity;
    //   38: aload 6
    //   40: iconst_3
    //   41: invokestatic 48	net/youmi/android/k:a	(Landroid/content/Context;Lnet/youmi/android/bw;I)V
    //   44: new 50	java/lang/StringBuilder
    //   47: dup
    //   48: ldc 52
    //   50: invokespecial 55	java/lang/StringBuilder:<init>	(Ljava/lang/String;)V
    //   53: aload_3
    //   54: invokevirtual 59	java/lang/StringBuilder:append	(Ljava/lang/String;)Ljava/lang/StringBuilder;
    //   57: invokevirtual 63	java/lang/StringBuilder:toString	()Ljava/lang/String;
    //   60: astore 5
    //   62: aload_0
    //   63: getfield 12	net/youmi/android/eg:a	Lnet/youmi/android/cb;
    //   66: getfield 40	net/youmi/android/cb:b	Landroid/app/Activity;
    //   69: aload 5
    //   71: invokestatic 68	net/youmi/android/be:a	(Landroid/app/Activity;Ljava/lang/String;)V
    //   74: return
    //   75: astore_2
    //   76: aload_2
    //   77: invokestatic 73	net/youmi/android/f:a	(Ljava/lang/Throwable;)V
    //   80: return
    //   81: astore 4
    //   83: goto -39 -> 44
    // Local variable table:
    //   start	length	slot	name	signature
    //   0	86	0	this	eg
    //   0	86	1	paramView	android.view.View
    //   75	2	2	localException1	java.lang.Exception
    //   13	41	3	str1	java.lang.String
    //   81	1	4	localException2	java.lang.Exception
    //   60	10	5	str2	java.lang.String
    //   29	10	6	localbw	bw
    // Exception table:
    //   from	to	target	type
    //   0	14	75	java/lang/Exception
    //   44	74	75	java/lang/Exception
    //   14	44	81	java/lang/Exception
  }
}


/* Location:           J:\android\tools\dex2jar-0.0.9.15\classes_dex2jar.jar
 * Qualified Name:     net.youmi.android.eg
 * JD-Core Version:    0.7.0.1
 */