package com.baidu;

class h
  extends Thread
{
  h(c paramc, t paramt) {}
  
  /* Error */
  public void run()
  {
    // Byte code:
    //   0: aload_0
    //   1: getfield 12	com/baidu/h:b	Lcom/baidu/c;
    //   4: invokestatic 27	com/baidu/c:a	(Lcom/baidu/c;)Lorg/json/JSONObject;
    //   7: astore_1
    //   8: aload_1
    //   9: monitorenter
    //   10: aload_0
    //   11: getfield 12	com/baidu/h:b	Lcom/baidu/c;
    //   14: invokestatic 27	com/baidu/c:a	(Lcom/baidu/c;)Lorg/json/JSONObject;
    //   17: ldc 29
    //   19: invokevirtual 35	org/json/JSONObject:getJSONObject	(Ljava/lang/String;)Lorg/json/JSONObject;
    //   22: astore 5
    //   24: aload 5
    //   26: invokevirtual 39	org/json/JSONObject:keys	()Ljava/util/Iterator;
    //   29: astore 6
    //   31: aload 6
    //   33: invokeinterface 45 1 0
    //   38: istore 7
    //   40: iload 7
    //   42: ifeq +317 -> 359
    //   45: aload 6
    //   47: invokeinterface 49 1 0
    //   52: invokevirtual 55	java/lang/Object:toString	()Ljava/lang/String;
    //   55: astore 12
    //   57: new 57	java/lang/StringBuilder
    //   60: dup
    //   61: invokespecial 58	java/lang/StringBuilder:<init>	()V
    //   64: ldc 60
    //   66: invokevirtual 64	java/lang/StringBuilder:append	(Ljava/lang/String;)Ljava/lang/StringBuilder;
    //   69: aload 12
    //   71: invokevirtual 64	java/lang/StringBuilder:append	(Ljava/lang/String;)Ljava/lang/StringBuilder;
    //   74: ldc 66
    //   76: invokevirtual 64	java/lang/StringBuilder:append	(Ljava/lang/String;)Ljava/lang/StringBuilder;
    //   79: invokevirtual 67	java/lang/StringBuilder:toString	()Ljava/lang/String;
    //   82: invokestatic 72	com/baidu/bk:b	(Ljava/lang/String;)I
    //   85: pop
    //   86: aload 5
    //   88: aload 12
    //   90: invokevirtual 35	org/json/JSONObject:getJSONObject	(Ljava/lang/String;)Lorg/json/JSONObject;
    //   93: astore 14
    //   95: aload 14
    //   97: ldc 74
    //   99: invokevirtual 78	org/json/JSONObject:getJSONArray	(Ljava/lang/String;)Lorg/json/JSONArray;
    //   102: astore 15
    //   104: iconst_m1
    //   105: aload 15
    //   107: invokevirtual 84	org/json/JSONArray:length	()I
    //   110: iadd
    //   111: istore 16
    //   113: iload 16
    //   115: iflt +247 -> 362
    //   118: aload 15
    //   120: iload 16
    //   122: invokevirtual 88	org/json/JSONArray:isNull	(I)Z
    //   125: ifeq +6 -> 131
    //   128: goto +346 -> 474
    //   131: aload 15
    //   133: iload 16
    //   135: invokevirtual 91	org/json/JSONArray:getJSONObject	(I)Lorg/json/JSONObject;
    //   138: astore 17
    //   140: iconst_5
    //   141: anewarray 51	java/lang/Object
    //   144: astore 18
    //   146: aload 18
    //   148: iconst_0
    //   149: aload 17
    //   151: ldc 93
    //   153: invokevirtual 96	org/json/JSONObject:getInt	(Ljava/lang/String;)I
    //   156: invokestatic 102	java/lang/Integer:valueOf	(I)Ljava/lang/Integer;
    //   159: aastore
    //   160: aload 18
    //   162: iconst_1
    //   163: aload 17
    //   165: ldc 29
    //   167: invokevirtual 96	org/json/JSONObject:getInt	(Ljava/lang/String;)I
    //   170: invokestatic 102	java/lang/Integer:valueOf	(I)Ljava/lang/Integer;
    //   173: aastore
    //   174: aload 18
    //   176: iconst_2
    //   177: aload 17
    //   179: ldc 104
    //   181: invokevirtual 96	org/json/JSONObject:getInt	(Ljava/lang/String;)I
    //   184: invokestatic 102	java/lang/Integer:valueOf	(I)Ljava/lang/Integer;
    //   187: aastore
    //   188: aload 18
    //   190: iconst_3
    //   191: aload_0
    //   192: getfield 14	com/baidu/h:a	Lcom/baidu/t;
    //   195: invokevirtual 108	com/baidu/t:b	()I
    //   198: invokestatic 102	java/lang/Integer:valueOf	(I)Ljava/lang/Integer;
    //   201: aastore
    //   202: aload 18
    //   204: iconst_4
    //   205: aload 17
    //   207: ldc 110
    //   209: invokevirtual 114	org/json/JSONObject:getString	(Ljava/lang/String;)Ljava/lang/String;
    //   212: aastore
    //   213: ldc 116
    //   215: aload 18
    //   217: invokestatic 122	java/lang/String:format	(Ljava/lang/String;[Ljava/lang/Object;)Ljava/lang/String;
    //   220: invokestatic 126	com/baidu/ax:a	(Ljava/lang/String;)Ljava/lang/String;
    //   223: astore 19
    //   225: new 57	java/lang/StringBuilder
    //   228: dup
    //   229: aload 14
    //   231: ldc 128
    //   233: invokevirtual 114	org/json/JSONObject:getString	(Ljava/lang/String;)Ljava/lang/String;
    //   236: invokespecial 131	java/lang/StringBuilder:<init>	(Ljava/lang/String;)V
    //   239: ldc 133
    //   241: invokevirtual 64	java/lang/StringBuilder:append	(Ljava/lang/String;)Ljava/lang/StringBuilder;
    //   244: aload 19
    //   246: invokevirtual 64	java/lang/StringBuilder:append	(Ljava/lang/String;)Ljava/lang/StringBuilder;
    //   249: invokevirtual 67	java/lang/StringBuilder:toString	()Ljava/lang/String;
    //   252: astore 20
    //   254: ldc 135
    //   256: new 57	java/lang/StringBuilder
    //   259: dup
    //   260: invokespecial 58	java/lang/StringBuilder:<init>	()V
    //   263: aload 12
    //   265: invokevirtual 64	java/lang/StringBuilder:append	(Ljava/lang/String;)Ljava/lang/StringBuilder;
    //   268: ldc 137
    //   270: invokevirtual 64	java/lang/StringBuilder:append	(Ljava/lang/String;)Ljava/lang/StringBuilder;
    //   273: aload 17
    //   275: ldc 139
    //   277: invokevirtual 114	org/json/JSONObject:getString	(Ljava/lang/String;)Ljava/lang/String;
    //   280: invokevirtual 64	java/lang/StringBuilder:append	(Ljava/lang/String;)Ljava/lang/StringBuilder;
    //   283: invokevirtual 67	java/lang/StringBuilder:toString	()Ljava/lang/String;
    //   286: invokestatic 142	com/baidu/bk:b	(Ljava/lang/String;Ljava/lang/String;)I
    //   289: pop
    //   290: ldc 135
    //   292: aload 20
    //   294: invokestatic 142	com/baidu/bk:b	(Ljava/lang/String;Ljava/lang/String;)I
    //   297: pop
    //   298: ldc 144
    //   300: invokestatic 148	com/baidu/c:q	()Ljava/lang/ref/WeakReference;
    //   303: invokevirtual 153	java/lang/ref/WeakReference:get	()Ljava/lang/Object;
    //   306: checkcast 155	android/content/Context
    //   309: aload 20
    //   311: invokestatic 161	com/baidu/w:d	(Landroid/content/Context;Ljava/lang/String;)Ljava/lang/String;
    //   314: invokevirtual 165	java/lang/String:equals	(Ljava/lang/Object;)Z
    //   317: ifne +157 -> 474
    //   320: aload 15
    //   322: iload 16
    //   324: getstatic 169	org/json/JSONObject:NULL	Ljava/lang/Object;
    //   327: invokevirtual 173	org/json/JSONArray:put	(ILjava/lang/Object;)Lorg/json/JSONArray;
    //   330: pop
    //   331: goto +143 -> 474
    //   334: astore 10
    //   336: ldc 135
    //   338: ldc 175
    //   340: aload 10
    //   342: invokestatic 178	com/baidu/bk:a	(Ljava/lang/String;Ljava/lang/String;Ljava/lang/Throwable;)I
    //   345: pop
    //   346: goto -315 -> 31
    //   349: astore_3
    //   350: ldc 135
    //   352: ldc 175
    //   354: aload_3
    //   355: invokestatic 178	com/baidu/bk:a	(Ljava/lang/String;Ljava/lang/String;Ljava/lang/Throwable;)I
    //   358: pop
    //   359: aload_1
    //   360: monitorexit
    //   361: return
    //   362: iconst_0
    //   363: istore 24
    //   365: iload 24
    //   367: aload 15
    //   369: invokevirtual 84	org/json/JSONArray:length	()I
    //   372: if_icmpge +96 -> 468
    //   375: aload 15
    //   377: iload 24
    //   379: invokevirtual 88	org/json/JSONArray:isNull	(I)Z
    //   382: ifne +80 -> 462
    //   385: iconst_0
    //   386: istore 25
    //   388: iload 25
    //   390: ifeq +36 -> 426
    //   393: aload 6
    //   395: invokeinterface 181 1 0
    //   400: ldc 135
    //   402: new 57	java/lang/StringBuilder
    //   405: dup
    //   406: invokespecial 58	java/lang/StringBuilder:<init>	()V
    //   409: aload 12
    //   411: invokevirtual 64	java/lang/StringBuilder:append	(Ljava/lang/String;)Ljava/lang/StringBuilder;
    //   414: ldc 183
    //   416: invokevirtual 64	java/lang/StringBuilder:append	(Ljava/lang/String;)Ljava/lang/StringBuilder;
    //   419: invokevirtual 67	java/lang/StringBuilder:toString	()Ljava/lang/String;
    //   422: invokestatic 142	com/baidu/bk:b	(Ljava/lang/String;Ljava/lang/String;)I
    //   425: pop
    //   426: aload_0
    //   427: getfield 12	com/baidu/h:b	Lcom/baidu/c;
    //   430: invokestatic 187	com/baidu/c:c	(Lcom/baidu/c;)V
    //   433: ldc 189
    //   435: invokestatic 72	com/baidu/bk:b	(Ljava/lang/String;)I
    //   438: pop
    //   439: goto -408 -> 31
    //   442: astore 8
    //   444: ldc 135
    //   446: ldc 175
    //   448: aload 8
    //   450: invokestatic 178	com/baidu/bk:a	(Ljava/lang/String;Ljava/lang/String;Ljava/lang/Throwable;)I
    //   453: pop
    //   454: goto -423 -> 31
    //   457: astore_2
    //   458: aload_1
    //   459: monitorexit
    //   460: aload_2
    //   461: athrow
    //   462: iinc 24 1
    //   465: goto -100 -> 365
    //   468: iconst_1
    //   469: istore 25
    //   471: goto -83 -> 388
    //   474: iinc 16 255
    //   477: goto -364 -> 113
    // Local variable table:
    //   start	length	slot	name	signature
    //   0	480	0	this	h
    //   7	452	1	localJSONObject1	org.json.JSONObject
    //   457	4	2	localObject	java.lang.Object
    //   349	6	3	localJSONException1	org.json.JSONException
    //   22	65	5	localJSONObject2	org.json.JSONObject
    //   29	365	6	localIterator	java.util.Iterator
    //   38	3	7	bool	boolean
    //   442	7	8	localException	java.lang.Exception
    //   334	7	10	localJSONException2	org.json.JSONException
    //   55	355	12	str1	java.lang.String
    //   93	137	14	localJSONObject3	org.json.JSONObject
    //   102	274	15	localJSONArray	org.json.JSONArray
    //   111	364	16	i	int
    //   138	136	17	localJSONObject4	org.json.JSONObject
    //   144	72	18	arrayOfObject	java.lang.Object[]
    //   223	22	19	str2	java.lang.String
    //   252	58	20	str3	java.lang.String
    //   363	100	24	j	int
    //   386	84	25	k	int
    // Exception table:
    //   from	to	target	type
    //   45	113	334	org/json/JSONException
    //   118	128	334	org/json/JSONException
    //   131	331	334	org/json/JSONException
    //   365	385	334	org/json/JSONException
    //   393	426	334	org/json/JSONException
    //   426	439	334	org/json/JSONException
    //   10	31	349	org/json/JSONException
    //   31	40	349	org/json/JSONException
    //   336	346	349	org/json/JSONException
    //   444	454	349	org/json/JSONException
    //   45	113	442	java/lang/Exception
    //   118	128	442	java/lang/Exception
    //   131	331	442	java/lang/Exception
    //   365	385	442	java/lang/Exception
    //   393	426	442	java/lang/Exception
    //   426	439	442	java/lang/Exception
    //   10	31	457	finally
    //   31	40	457	finally
    //   45	113	457	finally
    //   118	128	457	finally
    //   131	331	457	finally
    //   336	346	457	finally
    //   350	359	457	finally
    //   359	361	457	finally
    //   365	385	457	finally
    //   393	426	457	finally
    //   426	439	457	finally
    //   444	454	457	finally
    //   458	460	457	finally
  }
}


/* Location:           J:\android\tools\dex2jar-0.0.9.15\classes_dex2jar.jar
 * Qualified Name:     com.baidu.h
 * JD-Core Version:    0.7.0.1
 */